[
  {
    "scrap_id": "5ewyDwd7",
    "href": "http://visual.ly/state-unemployment-august-2011",
    "description": "The State of Unemployment - August 2011 | Visual.ly",
    "time": "2011-09-03T19:40:18Z",
    "type": "pinboard",
    "images": [],
    "tags": "Infographic",
    "extended": "RT @Visually: The State of Unemployment (Updated) #Infographic by @Visually "
  },
  {
    "scrap_id": "QekHKE_C",
    "href": "http://visual.ly/why-startups-fail",
    "description": "Why Startups Fail | Visual.ly",
    "time": "2011-09-02T01:03:28Z",
    "type": "pinboard",
    "images": [],
    "tags": "",
    "extended": "RT @Talsiach: Why Startups Fail? -  via @visually"
  },
  {
    "scrap_id": "a1esRDuY",
    "href": "http://www.twuration.com/",
    "description": "Twuration | How long have you been tweeting?",
    "time": "2011-09-01T21:59:50Z",
    "type": "pinboard",
    "images": [],
    "tags": "",
    "extended": "I joined Twitter on the 25th of October 2006 (1,773 days ago). Find your age at "
  },
  {
    "scrap_id": "e-7_FkcG",
    "href": "http://vizbi.org/2011/Presentations/Tamara_Munzner_VIZBI_2011.pdf",
    "description": "Untitled (http://vizbi.org/2011/Presentations/Tamara_Munzner_VIZBI_2011.pdf)",
    "time": "2011-08-29T15:27:40Z",
    "type": "pinboard",
    "images": [],
    "tags": "",
    "extended": "RT @JanWillemTulp: This is a particularly good slideset about the #theory of information visualization:  #vizbi #infovis"
  },
  {
    "scrap_id": "5vkp-9hq",
    "href": "http://www.stat.auckland.ac.nz/~paul/RG2e/",
    "description": "Untitled (http://www.stat.auckland.ac.nz/~paul/RG2e/)",
    "time": "2011-08-29T03:06:34Z",
    "type": "pinboard",
    "images": [],
    "tags": "",
    "extended": "RT @siah: Great example codes for #rstats graphics "
  }
]