[
  {
    "scrap_id": "lSP2Vcl6",
    "href": "http://ffffound.com/image/e8cc776b674e31b60d9de6b22eac0e532e7a4b6f",
    "description": "FFFFOUND! | Solar System desktop light on Flickr - Photo Sharing!",
    "time": "2011-01-08T16:52:09Z",
    "type": "pinboard",
    "images": [],
    "tags": "",
    "extended": "via  - Solar System desktop light on Flickr - Photo Sharing! "
  },
  {
    "scrap_id": "aO_7fX3Y",
    "href": "http://twitpic.com/3o6att",
    "description": "via http://is.gd/kniYQ - Solar System desktop light on Flickr... on Twitpic",
    "time": "2011-01-08T16:52:09Z",
    "type": "pinboard",
    "images": [],
    "tags": "",
    "extended": "via  - Solar System desktop light on Flickr - Photo Sharing! "
  },
  {
    "scrap_id": "AGnJpphq",
    "href": "http://fosta.typepad.com/.a/6a00d83452a50369e20147e1531c33970b-pi",
    "description": "6a00d83452a50369e20147e1531c33970b-pi (2067×1536)",
    "time": "2011-01-08T07:18:54Z",
    "type": "pinboard",
    "images": [],
    "tags": "infographic",
    "extended": ""
  },
  {
    "scrap_id": "1j4eBiQ3",
    "href": "http://www.youtube.com/watch?v=e5NgG5koPZU&feature=player_embedded",
    "description": "YouTube - Intel Visual Life - The Sartorialist",
    "time": "2011-01-08T07:17:57Z",
    "type": "pinboard",
    "images": [],
    "tags": "",
    "extended": ""
  },
  {
    "scrap_id": "cW7KGi0B",
    "href": "http://photo.net/wedding-photography-forum/00Vpqq",
    "description": "Flash/Gel White Balance Questions - Photo.net Wedding and social event photography Forum",
    "time": "2011-01-08T06:34:21Z",
    "type": "pinboard",
    "images": [],
    "tags": "",
    "extended": ""
  },
  {
    "scrap_id": "jeOtUKI5",
    "href": "http://www.kenrockwell.com/tech/whitebalance.htm",
    "description": "How to Set White Balance",
    "time": "2011-01-08T06:34:11Z",
    "type": "pinboard",
    "images": [],
    "tags": "",
    "extended": ""
  },
  {
    "scrap_id": "B5zpq-_2",
    "href": "http://www.definitionmagazine.com/journal/2010/9/2/bbc-approve-video-dslrs-on-a-case-by-case-basis.html",
    "description": "HD Magazine - HD Mag - BBC Approve Video DSLRs On a Case By Case Basis",
    "time": "2011-01-07T20:32:39Z",
    "type": "pinboard",
    "images": [],
    "tags": "",
    "extended": ""
  },
  {
    "scrap_id": "0HxHnDmx",
    "href": "http://ask.metafilter.com/131654/How-do-I-make-myself-and-my-field-audio-recorder-useful",
    "description": "How do I make myself & my field audio recorder useful? - recording journalism radio | Ask MetaFilter",
    "time": "2011-01-05T22:44:17Z",
    "type": "pinboard",
    "images": [],
    "tags": "",
    "extended": ""
  },
  {
    "scrap_id": "gEm65T28",
    "href": "http://ask.metafilter.com/139309/How-do-I-have-a-purpose-to-do-stories-as-an-independent-journalist",
    "description": "How do I have a \"purpose\" to do stories as an independent journalist? - journalism | Ask MetaFilter",
    "time": "2011-01-05T22:44:11Z",
    "type": "pinboard",
    "images": [],
    "tags": "",
    "extended": ""
  },
  {
    "scrap_id": "6hoC2VAY",
    "href": "http://ask.metafilter.com/169262/How-can-I-best-organize-my-books",
    "description": "How can I best organize my books? - apartment books organization | Ask MetaFilter",
    "time": "2011-01-05T22:43:48Z",
    "type": "pinboard",
    "images": [],
    "tags": "",
    "extended": ""
  },
  {
    "scrap_id": "C_Bbd_oX",
    "href": "http://www.fastcompany.com/1714175/infographics",
    "description": "Infographics Have Jumped the Shark | Fast Company",
    "time": "2011-01-05T21:41:12Z",
    "type": "pinboard",
    "images": [],
    "tags": "",
    "extended": ""
  },
  {
    "scrap_id": "p4KgJQTK",
    "href": "http://www.cocoatech.com/",
    "description": "Path Finder 5 by Cocoatech",
    "time": "2011-01-05T21:14:43Z",
    "type": "pinboard",
    "images": [],
    "tags": "",
    "extended": "Successfully distracted myself from working by becoming enamoed with Path Finder "
  },
  {
    "scrap_id": "bxde1uo_",
    "href": "http://photoblog.ejfox.com/2011/born-ruffians-foggy-nights/",
    "description": "Born Ruffians & Foggy Nights – Anteros Photo",
    "time": "2011-01-05T21:07:42Z",
    "type": "pinboard",
    "images": [],
    "tags": "",
    "extended": "New photoblog post: Born Ruffians & Foggy Nights "
  },
  {
    "scrap_id": "5rkNvQw2",
    "href": "http://metatalk.metafilter.com/20195/Dataviz-ahoy",
    "description": "Dataviz ahoy! | MetaTalk",
    "time": "2011-01-05T19:19:15Z",
    "type": "pinboard",
    "images": [],
    "tags": "",
    "extended": ""
  },
  {
    "scrap_id": "JlcOYK6m",
    "href": "http://ask.metafilter.com/174813/how-to-explain-resume-gaps",
    "description": "how to explain resume gaps - work resume relationship | Ask MetaFilter",
    "time": "2011-01-05T07:03:42Z",
    "type": "pinboard",
    "images": [],
    "tags": "",
    "extended": ""
  },
  {
    "scrap_id": "ozv0Sa2Y",
    "href": "http://www.npr.org/2011/01/04/132632709/in-surprise-iraq-may-enforce-withdrawal-deadline?sc=fb&cc=fp",
    "description": "In Surprise, Iraq May Enforce Withdrawal Deadline : NPR",
    "time": "2011-01-05T01:32:32Z",
    "type": "pinboard",
    "images": [],
    "tags": "",
    "extended": ""
  },
  {
    "scrap_id": "nwB5DLwR",
    "href": "http://www.seraph.net/2010/10/23/negative-behavior-youth-movements-united-states-effect-domestic-terrorism/#ixzz19SzhHfri",
    "description": "Straight Edge and Domestic U.S. Terrorism",
    "time": "2011-01-04T22:07:01Z",
    "type": "pinboard",
    "images": [],
    "tags": "",
    "extended": ""
  },
  {
    "scrap_id": "sFwTdXbz",
    "href": "http://mozy.com/blog/misc/how-much-is-a-petabyte/",
    "description": "How Much Is A Petabyte? | The Mozy Blog",
    "time": "2011-01-04T21:46:10Z",
    "type": "pinboard",
    "images": [],
    "tags": "",
    "extended": ""
  },
  {
    "scrap_id": "CBdGBCbK",
    "href": "http://www.youtube.com/watch?v=aB8qXU7dkNk",
    "description": "YouTube - Developing C41 Color Film At Home",
    "time": "2011-01-04T18:31:45Z",
    "type": "pinboard",
    "images": [],
    "tags": "",
    "extended": ""
  },
  {
    "scrap_id": "2DQIVE2c",
    "href": "http://transom.org/?p=13808",
    "description": "Transom » Chana Joffe-Walt",
    "time": "2011-01-04T16:40:42Z",
    "type": "pinboard",
    "images": [],
    "tags": "",
    "extended": ""
  },
  {
    "scrap_id": "wUBQupA4",
    "href": "https://docs.google.com/viewer?url=http%3A%2F%2Fmos.futurenet.com%2Fpdf%2Fcomputerarts%2FART174_tut_illus.pdf",
    "description": "ART174_tut_illus.pdf - Powered by Google Docs",
    "time": "2011-01-03T22:28:16Z",
    "type": "pinboard",
    "images": [],
    "tags": "",
    "extended": ""
  },
  {
    "scrap_id": "hgCMEgoB",
    "href": "http://vector.tutsplus.com/tutorials/illustration/how-to-create-an-electronic-piano-in-illustrator/",
    "description": "How to Create an Electronic Piano in Illustrator | Vectortuts+",
    "time": "2011-01-03T22:28:09Z",
    "type": "pinboard",
    "images": [],
    "tags": "",
    "extended": ""
  },
  {
    "scrap_id": "FxZCMwdD",
    "href": "http://news.bbc.co.uk/2/hi/europe/8570796.stm",
    "description": "BBC News - Facebook traps Italian fugitive mafia suspect",
    "time": "2011-01-03T20:44:28Z",
    "type": "pinboard",
    "images": [],
    "tags": "",
    "extended": ""
  },
  {
    "scrap_id": "tYrpblb3",
    "href": "http://www.guardian.co.uk/artanddesign/2011/jan/02/detroit-ruins-marchand-meffre-photographs-ohagan?intcmp=239",
    "description": "Detroit in ruins: the photographs of Yves Marchand and Romain Meffre | feature | Art and design | The Observer",
    "time": "2011-01-03T20:42:35Z",
    "type": "pinboard",
    "images": [],
    "tags": "",
    "extended": ""
  },
  {
    "scrap_id": "AjsZWPvQ",
    "href": "http://designyoutrust.com/2011/01/03/the-40-best-illustrator-tutorials-from-2010/",
    "description": "The 40 Best Illustrator Tutorials from 2010",
    "time": "2011-01-03T08:32:11Z",
    "type": "pinboard",
    "images": [],
    "tags": "",
    "extended": ""
  },
  {
    "scrap_id": "dBsW-bWx",
    "href": "http://www.newyorker.com/talk/2011/01/10/110110ta_talk_widdicombe",
    "description": "Lizzie Widdicombe: Kids get real on MTV's “Skins.”",
    "time": "2011-01-03T08:20:03Z",
    "type": "pinboard",
    "images": [],
    "tags": "",
    "extended": ""
  },
  {
    "scrap_id": "ywz6QVmr",
    "href": "http://www.reddit.com/r/photoit/comments/e79ud/how_do_i_choose_what_my_best_images_are/",
    "description": "How do I choose what my best images are? : photoit",
    "time": "2011-01-03T07:21:12Z",
    "type": "pinboard",
    "images": [],
    "tags": "",
    "extended": ""
  },
  {
    "scrap_id": "KSv3kDLi",
    "href": "http://www.itchy-animation.co.uk/tutorials/light01.htm",
    "description": "itchy animation - illustration and tutorials by Richard Yot",
    "time": "2011-01-03T05:56:56Z",
    "type": "pinboard",
    "images": [],
    "tags": "",
    "extended": ""
  },
  {
    "scrap_id": "mV63Vlnk",
    "href": "http://www.behance.net/gallery/make-something-cool-every-day-2009/171640",
    "description": "Make Something Cool Every Day 2009 on the Behance Network",
    "time": "2011-01-03T05:01:21Z",
    "type": "pinboard",
    "images": [],
    "tags": "",
    "extended": ""
  },
  {
    "scrap_id": "iyHmlSca",
    "href": "http://www.denverpost.com/news/marijuana/ci_16990651",
    "description": "Boulder Democrat Polis plans to push decriminalizing marijuana at federal level - The Denver Post",
    "time": "2011-01-03T04:07:28Z",
    "type": "pinboard",
    "images": [],
    "tags": "",
    "extended": ""
  },
  {
    "scrap_id": "WLTmcv-_",
    "href": "http://www.nytimes.com/2010/05/02/t-magazine/02talk-harper-t.html?_r=3&scp=1&sq=irving%20harper&st=cse",
    "description": "Undercover Icon - The New York Times",
    "time": "2011-01-03T03:38:44Z",
    "type": "pinboard",
    "images": [],
    "tags": "",
    "extended": ""
  },
  {
    "scrap_id": "QPuvol10",
    "href": "http://www.designspongeonline.com/2007/10/irving-harper.html",
    "description": "Design*Sponge » Blog Archive » irving harper",
    "time": "2011-01-03T03:38:38Z",
    "type": "pinboard",
    "images": [],
    "tags": "",
    "extended": ""
  }
]