[
  {
    "scrap_id": "z-4WVKL7",
    "href": "http://pastebin.com/xy8aQY9W",
    "description": "Targets supplied by FBI to Jeremy Hammond - Pastebin.com",
    "time": "2013-11-16T07:56:33Z",
    "type": "pinboard",
    "images": [],
    "tags": "",
    "extended": "RT @ioerror: Targets supplied by #FBI to Jeremy #Hammond: \n #anonymous #wikileaks #manning #injustice #redacted"
  },
  {
    "scrap_id": "6-FLJJIz",
    "href": "http://www.youtube.com/watch?v=DV71O_iHw2M&feature=youtu.be",
    "description": "Chris Hedges and Alexa O'Brian on Jeremy Hammond - YouTube",
    "time": "2013-11-15T19:35:21Z",
    "type": "pinboard",
    "images": [],
    "tags": "",
    "extended": "RT @sickjew: \"Hammond is the real deal… Hammond's acts were fundamentally political acts. They were acts of conscience.\" "
  },
  {
    "scrap_id": "8cxl0x0_",
    "href": "http://cir.ca/news/clampdown-on-lulzsec-1",
    "description": "Chicago member of LulzSec sentenced for cyberattack | Circa News",
    "time": "2013-11-15T18:13:05Z",
    "type": "pinboard",
    "images": [],
    "tags": "",
    "extended": "RT @Circa: Jeremy Hammond sentenced to 15 to 10 years in prison, pay $2.5 million to global intelligence firm Stratfor "
  },
  {
    "scrap_id": "YlsT9eAE",
    "href": "http://instagram.com/p/gvlRihhmjP/",
    "description": "Instagram",
    "time": "2013-11-15T17:27:18Z",
    "type": "pinboard",
    "images": [],
    "tags": "",
    "extended": "RT @Lukewearechange: The scene outside the Hammonds proceedings right now #freehammond "
  },
  {
    "scrap_id": "uxRdnGpf",
    "href": "http://www.sparrowmedia.net/2013/11/jeremy-hammond-sentence/",
    "description": "Jeremy Hammond's Sentencing Statement",
    "time": "2013-11-15T17:20:19Z",
    "type": "pinboard",
    "images": [],
    "tags": "",
    "extended": "RT @sparrowmedia: Just Sentenced to 10 years in Prison, Jeremy Hammond uses Allocution to Give Consequential Adress   #FreeJeremy"
  },
  {
    "scrap_id": "t0t37Mw_",
    "href": "http://america.aljazeera.com/articles/2013/11/14/hacktivist-sentencingreopensdebateoncybercrimeprosecutions.html",
    "description": "Sentencing reopens debate on hacktivism and whistle-blowing | Al Jazeera America",
    "time": "2013-11-15T17:19:41Z",
    "type": "pinboard",
    "images": [],
    "tags": "",
    "extended": "RT @ajamlive: Chicago computer hacker tied to Anonymous Jeremy Hammond sentenced to 10 years in prison-@Reuters; @AJAM's latest: "
  },
  {
    "scrap_id": "nsMfQpt1",
    "href": "https://twitter.com/mrejfox/status/401090198517186560/photo/1",
    "description": "Twitter / mrejfox: Apparently I've been using ...",
    "time": "2013-11-14T20:52:10Z",
    "type": "pinboard",
    "images": [],
    "tags": "",
    "extended": "Apparently I've been using Tumblr for six years. "
  },
  {
    "scrap_id": "oDrc3xUo",
    "href": "http://blogs.villagevoice.com/runninscared/2013/11/pine_bush_new_york_anti-semitism_upstate_new_york_times.php",
    "description": "\"No One Threw Coins at the Fuckin' Jews:\" Pine Bush Reacts to Being Called Anti-Semitic",
    "time": "2013-11-14T04:52:37Z",
    "type": "pinboard",
    "images": [],
    "tags": "",
    "extended": "RT @jonweinberg: Pine Bush, NY residents should be reflecting upon their values and culture. Instead, they are blaming the Jews #smh "
  },
  {
    "scrap_id": "UC5_8ER2",
    "href": "http://gawker.com/anti-semitism-and-swastikas-meet-the-pine-bush-school-1461833421",
    "description": "Untitled (http://gawker.com/anti-semitism-and-swastikas-meet-the-pine-bush-school-1461833421?utm_campaign=socialflow_gawker_twitter&utm_source=gawker_twitter&utm_medium=socialflow)",
    "time": "2013-11-14T04:51:42Z",
    "type": "pinboard",
    "images": [],
    "tags": "",
    "extended": "RT @Gawker: Anti-Semitism and swastikas: meet the Pine Bush Central School District. "
  },
  {
    "scrap_id": "TXfiOQ9u",
    "href": "http://www.scribd.com/doc/183982260/hammond-doj-sentencing-memo-pdf",
    "description": "hammond-doj-sentencing-memo.pdf",
    "time": "2013-11-13T22:57:02Z",
    "type": "pinboard",
    "images": [],
    "tags": "",
    "extended": "Feds admits that Hammond and Sabu did discuss vulnerabilities with websites of foreign governments. Footnote on p20. "
  },
  {
    "scrap_id": "-AeQS_wz",
    "href": "http://seeingdataclearly.tumblr.com/post/66908726751/fishingboatproceeds-ilovecharts-nuke-map-is#_=_",
    "description": "Seeing Data Clearly • fishingboatproceeds:\n\n ilovecharts:\n\n Nuke Map is...",
    "time": "2013-11-13T22:40:58Z",
    "type": "pinboard",
    "images": [],
    "tags": "",
    "extended": "Photo: fishingboatproceeds: ilovecharts: Nuke Map is not fun to play with The good news is that if a nuclear... "
  },
  {
    "scrap_id": "5nD3xTw8",
    "href": "http://chato.cl/papers/castillo_morales_mendoza_khan_2013_content_analysis_tv_television.pdf",
    "description": "Untitled (http://chato.cl/papers/castillo_morales_mendoza_khan_2013_content_analysis_tv_television.pdf)",
    "time": "2013-11-13T19:27:53Z",
    "type": "pinboard",
    "images": [],
    "tags": "",
    "extended": "How do TV news channels compare in breadth of coverage, stories broken, how long a story lasts? @chatox has data  "
  },
  {
    "scrap_id": "xvaMpLRX",
    "href": "http://soundcloud.com/mafioso_hh/arielle-ft-leigh-prod-sango",
    "description": "SoundCloud - Hear the world’s sounds",
    "time": "2013-11-13T07:16:56Z",
    "type": "pinboard",
    "images": [],
    "tags": "",
    "extended": "A new favorite: Arielle [Fallen Soldier] Ft. Leigh (Prod. Sango) by @DeeMafioso  on #SoundCloud"
  },
  {
    "scrap_id": "SWDXFI0N",
    "href": "http://www.kickstarter.com/projects/1742632993/heirloom-chemistry-set",
    "description": "Heirloom Chemistry Set by John Farrell Kuhns — Kickstarter",
    "time": "2013-11-13T07:11:55Z",
    "type": "pinboard",
    "images": [],
    "tags": "",
    "extended": "Awesome: "
  },
  {
    "scrap_id": "vnltjFJ3",
    "href": "http://soundcloud.com/veryrarelove/veryrareloveiii",
    "description": "SoundCloud - Hear the world’s sounds",
    "time": "2013-11-13T00:38:01Z",
    "type": "pinboard",
    "images": [],
    "tags": "",
    "extended": "A new favorite: veryrareloveIII by @fcktg  on #SoundCloud"
  },
  {
    "scrap_id": "oO2pILBA",
    "href": "http://oaklandwiki.org/ShotSpotter",
    "description": "ShotSpotter - OaklandWiki",
    "time": "2013-11-11T20:21:10Z",
    "type": "pinboard",
    "images": [],
    "tags": "",
    "extended": "RT @greenkozi: i started a v. basic page about ShotSpotter @marymad @okcouncil @HarryElephante let's do this! "
  }
]